<keymap version="1" name="Xremap">
  <action id="$Copy">
    <keyboard-shortcut first-keystroke="alt c" />
  </action>
  <action id="$Paste">
    <keyboard-shortcut first-keystroke="alt v" />
  </action>
  <action id="ActivateProjectToolWindow" />
  <action id="CloseContent">
    <keyboard-shortcut first-keystroke="alt w" />
  </action>
  <action id="Console.TableResult.NavigateAction" />
  <action id="Console.TableResult.NavigateForeignAction">
    <mouse-shortcut keystroke="control button1" />
  </action>
  <action id="DatabaseView.OpenFamilyAction" />
  <action id="Diff.FocusOppositePane" />
  <action id="Diff.FocusOppositePaneAndScroll" />
  <action id="Documentation.EditSource" />
  <action id="DomCollectionControl.Edit" />
  <action id="DomElementsTreeView.GotoDomElementDeclarationAction" />
  <action id="Editor Copy">
    <keyboard-shortcut first-keystroke="alt c" />
  </action>
  <action id="Editor Paste">
    <keyboard-shortcut first-keystroke="alt v" />
  </action>
  <action id="EditorDeleteToWordEnd">
    <keyboard-shortcut first-keystroke="alt d" />
  </action>
  <action id="EditorEscape">
    <keyboard-shortcut first-keystroke="escape" />
    <keyboard-shortcut first-keystroke="ctrl c" />
  </action>
  <action id="EditorLeft">
    <keyboard-shortcut first-keystroke="left" />
    <keyboard-shortcut first-keystroke="ctrl b" />
  </action>
  <action id="EditorRight">
    <keyboard-shortcut first-keystroke="right" />
    <keyboard-shortcut first-keystroke="ctrl f" />
  </action>
  <action id="EditorSelectWord" />
  <action id="ExportToTextFile" />
  <action id="ExternalSystem.OpenConfig" />
  <action id="Find">
    <keyboard-shortcut first-keystroke="ctrl s" />
  </action>
  <action id="GotoDeclaration">
    <mouse-shortcut keystroke="control button1" />
    <keyboard-shortcut first-keystroke="alt at" />
  </action>
  <action id="HideActiveWindow" />
  <action id="Jdbc.OpenEditor.Console" />
  <action id="Jdbc.OpenEditor.Data" />
  <action id="NavBar-navigate" />
  <action id="NextSplitter">
    <keyboard-shortcut first-keystroke="ctrl w" second-keystroke="l" />
  </action>
  <action id="NextTab">
    <keyboard-shortcut first-keystroke="alt p" />
  </action>
  <action id="PrevSplitter">
    <keyboard-shortcut first-keystroke="ctrl w" second-keystroke="h" />
  </action>
  <action id="PreviousTab">
    <keyboard-shortcut first-keystroke="alt o" />
  </action>
  <action id="ProjectViewEditSource" />
  <action id="RemoteHostView.EditSource" />
  <action id="SaveAll">
    <keyboard-shortcut first-keystroke="alt s" />
  </action>
  <action id="Scala.ShowImplicits">
    <keyboard-shortcut first-keystroke="shift ctrl alt equals" />
    <keyboard-shortcut first-keystroke="shift ctrl alt add" />
  </action>
  <action id="ShowSettings">
    <keyboard-shortcut first-keystroke="alt comma" />
  </action>
  <action id="SmartSelect" />
  <action id="Sql.EditParameter" />
  <action id="Switcher" />
  <action id="TableResult.GrowSelection" />
  <action id="Terminal.CopySelectedText">
    <keyboard-shortcut first-keystroke="shift ctrl c" />
    <keyboard-shortcut first-keystroke="ctrl insert" />
  </action>
  <action id="UsageFiltering.WriteAccess" />
  <action id="Vcs.EditSource" />
  <action id="Vcs.UpdateProject" />
  <action id="XDebugger.JumpToSource" />
</keymap>